DOC.md
README.md
setup.py
orangepipes/__init__.py
orangepipes/helper.py
orangepipes/pipeline.py
orangepipes.egg-info/PKG-INFO
orangepipes.egg-info/SOURCES.txt
orangepipes.egg-info/dependency_links.txt
orangepipes.egg-info/requires.txt
orangepipes.egg-info/top_level.txt