Metadata-Version: 2.1
Name: orangepipes
Version: 0.1.8
Summary: Python library to read an orange.yml file and write the variables to the system.
Home-page: UNKNOWN
License: MIT
Platform: UNKNOWN
